testcontainers_on_whales-0.7.0.dist-info/METADATA
testcontainers_on_whales-0.7.0.dist-info/WHEEL
testcontainers_on_whales-0.7.0.dist-info/licenses/LICENSE
testcontainers_on_whales/__init__.py
testcontainers_on_whales/__version__.py
testcontainers_on_whales/core/__init__.py
testcontainers_on_whales/core/container.py
testcontainers_on_whales/core/exceptions.py
testcontainers_on_whales/eventstoredb.py
testcontainers_on_whales/minio.py
testcontainers_on_whales/nginx.py
testcontainers_on_whales/postgres.py
testcontainers_on_whales/py.typed
testcontainers_on_whales/rabbitmq.py
testcontainers_on_whales/redis.py
testcontainers_on_whales-0.7.0.dist-info/RECORD
