Metadata-Version: 2.1
Name: testcontainers-on-whales
Version: 0.7.0
Summary: A library that provides throwaway instances of common services.
Keywords: testing containers podman docker test automation
Author-Email: betaboon <betaboon@0x80.ninja>
Maintainer-Email: betaboon <betaboon@0x80.ninja>
License: MIT
Classifier: Development Status :: 4 - Beta
Classifier: Intended Audience :: Developers
Classifier: License :: OSI Approved :: MIT License
Classifier: Natural Language :: English
Classifier: Operating System :: OS Independent
Classifier: Programming Language :: Python
Classifier: Programming Language :: Python :: 3
Classifier: Programming Language :: Python :: 3 :: Only
Classifier: Programming Language :: Python :: 3.9
Classifier: Programming Language :: Python :: 3.10
Classifier: Programming Language :: Python :: 3.11
Classifier: Programming Language :: Python :: 3.12
Classifier: Typing :: Typed
Classifier: Topic :: Software Development :: Build Tools
Project-URL: Homepage, https://github.com/betaboon/testcontainers-on-whales
Project-URL: Documentation, https://betaboon.github.io/testcontainers-on-whales
Project-URL: Changelog, https://github.com/betaboon/testcontainers-on-whales/releases
Project-URL: Repository, https://github.com/betaboon/testcontainers-on-whales
Project-URL: Issue tracker, https://github.com/betaboon/testcontainers-on-whales/issues
Requires-Python: <3.13,>=3.9
Requires-Dist: python-on-whales>=0.69.0
Requires-Dist: requests>=2.31.0
Requires-Dist: eventstoredb>=0.8.1; extra == "eventstoredb"
Requires-Dist: boto3>=1.34.52; extra == "minio"
Requires-Dist: psycopg2-binary>=2.9.9; extra == "postgres"
Requires-Dist: sqlalchemy>=2.0.27; extra == "postgres"
Requires-Dist: pika>=1.3.2; extra == "rabbitmq"
Requires-Dist: redis>=5.0.2; extra == "redis"
Requires-Dist: testcontainers-on-whales[eventstoredb]; extra == "all"
Requires-Dist: testcontainers-on-whales[minio]; extra == "all"
Requires-Dist: testcontainers-on-whales[postgres]; extra == "all"
Requires-Dist: testcontainers-on-whales[rabbitmq]; extra == "all"
Requires-Dist: testcontainers-on-whales[redis]; extra == "all"
Provides-Extra: eventstoredb
Provides-Extra: minio
Provides-Extra: postgres
Provides-Extra: rabbitmq
Provides-Extra: redis
Provides-Extra: all
